{
  "app": {
    "[project]/admin/app/(dashboard)/audit-logs/page": [
      "static/media/83afe278b6a6bb3c-s.p.3a6ba036.woff2"
    ],
    "[project]/admin/app/(dashboard)/page": [
      "static/media/83afe278b6a6bb3c-s.p.3a6ba036.woff2"
    ],
    "[project]/admin/app/(dashboard)/restaurants/[id]/edit/page": [
      "static/media/83afe278b6a6bb3c-s.p.3a6ba036.woff2"
    ],
    "[project]/admin/app/(dashboard)/restaurants/new/page": [
      "static/media/83afe278b6a6bb3c-s.p.3a6ba036.woff2"
    ],
    "[project]/admin/app/(dashboard)/restaurants/page": [
      "static/media/83afe278b6a6bb3c-s.p.3a6ba036.woff2"
    ],
    "[project]/admin/app/(dashboard)/users/[id]/page": [
      "static/media/83afe278b6a6bb3c-s.p.3a6ba036.woff2"
    ],
    "[project]/admin/app/(dashboard)/users/page": [
      "static/media/83afe278b6a6bb3c-s.p.3a6ba036.woff2"
    ],
    "[project]/admin/app/(dashboard)/vouchers/page": [
      "static/media/83afe278b6a6bb3c-s.p.3a6ba036.woff2"
    ],
    "[project]/admin/app/_not-found/page": [
      "static/media/83afe278b6a6bb3c-s.p.3a6ba036.woff2"
    ],
    "[project]/admin/app/login/page": [
      "static/media/83afe278b6a6bb3c-s.p.3a6ba036.woff2"
    ],
    "[project]/admin/app/page": [
      "static/media/83afe278b6a6bb3c-s.p.3a6ba036.woff2"
    ]
  },
  "appUsingSizeAdjust": true,
  "pages": {},
  "pagesUsingSizeAdjust": false
}